{
  "title": "Desperate Battle at Starship",
  "narrative": "Alien artifacts pulse with energy as desperate battle at starship unfolds in the starship.",
  "choices": [
    {
      "text": "Fight bravely and face the challenge head-on",
      "effect": {
        "risk": 20,
        "reward": 30
      },
      "consequence": "brave_combat"
    },
    {
      "text": "Use strategy and cunning to outmaneuver your opponent",
      "effect": {
        "strategy": 15,
        "risk": 10
      },
      "consequence": "strategic_combat"
    },
    {
      "text": "Attempt to flee and live to fight another day",
      "effect": {
        "cowardice": 10,
        "safety": 15
      },
      "consequence": "retreat_combat"
    }
  ],
  "difficulty": "normal",
  "type": "BATTLE",
  "tags": [
    "space-opera",
    "starship",
    "battle",
    "fight",
    "battle"
  ],
  "context_requirements": {
    "location": "starship"
  }
}